odoo/addons/iot_output/README.rst
odoo/addons/iot_output/__init__.py
odoo/addons/iot_output/__manifest__.py
odoo/addons/iot_output/i18n/iot_output.pot
odoo/addons/iot_output/models/__init__.py
odoo/addons/iot_output/models/iot_device.py
odoo/addons/iot_output/models/iot_device_output.py
odoo/addons/iot_output/models/iot_device_output_action.py
odoo/addons/iot_output/models/iot_system.py
odoo/addons/iot_output/readme/CONTRIBUTORS.rst
odoo/addons/iot_output/readme/DESCRIPTION.rst
odoo/addons/iot_output/security/ir.model.access.csv
odoo/addons/iot_output/static/description/icon.png
odoo/addons/iot_output/static/description/index.html
odoo/addons/iot_output/tests/__init__.py
odoo/addons/iot_output/tests/test_iot.py
odoo/addons/iot_output/views/iot_device_output_views.xml
odoo/addons/iot_output/views/iot_device_views.xml
odoo/addons/iot_output/views/iot_menu.xml
odoo/addons/iot_output/views/iot_system_views.xml
odoo11_addon_iot_output-11.0.1.0.0.99.dev3.dist-info/METADATA
odoo11_addon_iot_output-11.0.1.0.0.99.dev3.dist-info/WHEEL
odoo11_addon_iot_output-11.0.1.0.0.99.dev3.dist-info/top_level.txt
odoo11_addon_iot_output-11.0.1.0.0.99.dev3.dist-info/RECORD
